pumpfun/__init__.py
pumpfun/api.py
pumpfun/client.py
pumpfun/config.py
pumpfun-0.3.dist-info/LICENSE
pumpfun-0.3.dist-info/METADATA
pumpfun-0.3.dist-info/WHEEL
pumpfun-0.3.dist-info/top_level.txt
pumpfun-0.3.dist-info/RECORD
